LICENSE
MANIFEST.in
README.md
pyproject.toml
requirements.txt
setup.py
tests/test_batching.py
tests/test_client.py
tests/test_errfile.py
tests/test_pack.py
tests/test_process.py
tests/test_server.py
tests/test_socket.py
tests/test_thread.py
twist/__init__.py
twist/batching.py
twist/buffers.py
twist/client.py
twist/client_socket.py
twist/contextlib.py
twist/packlib.py
twist/poollib.py
twist/process.py
twist/server.py
twist/server_socket.py
twist/sharray.py
twist/thread.py
twist/utils.py
twist.egg-info/PKG-INFO
twist.egg-info/SOURCES.txt
twist.egg-info/dependency_links.txt
twist.egg-info/requires.txt
twist.egg-info/top_level.txt