Metadata-Version: 2.1
Name: twist
Version: 0.1.0
Summary: Fast and reliable distributed systems in Python
Home-page: http://github.com/danijar/twist
Author: Danijar Hafner
Author-email: mail@danijar.com
Classifier: Intended Audience :: Science/Research
Classifier: License :: OSI Approved :: MIT License
Classifier: Programming Language :: Python :: 3
License-File: LICENSE
